cleaREST-0.3.5.dist-info/DESCRIPTION.rst
cleaREST-0.3.5.dist-info/METADATA
cleaREST-0.3.5.dist-info/RECORD
cleaREST-0.3.5.dist-info/WHEEL
cleaREST-0.3.5.dist-info/metadata.json
cleaREST-0.3.5.dist-info/top_level.txt
clearest/__init__.py
clearest/core.py
clearest/docs.py
clearest/exceptions.py
clearest/http.py
clearest/wsgi.py
clearest/templates/base.html
clearest/templates/index.html
clearest/templates/single.html
sample/__init__.py
sample/demo_simple_docs.py
sample/demo_simple_get.py
sample/demo_simple_post_var.py
tests/__init__.py
tests/test_application.py
tests/test_docs.py
tests/test_exceptions.py
tests/test_http_exceptions.py
tests/test_static.py
tests/util.py
tests/wsgi.py
