Metadata-Version: 2.0
Name: cleaREST
Version: 0.3.5
Summary: Light-weight Python framework for building REST APIs.
Home-page: https://github.com/petr-s/cleaREST
Author: Petr Skramovsky
Author-email: petr.skramovsky@gmail.com
License: MIT
Keywords: rest api framework json xml
Platform: UNKNOWN
Classifier: Development Status :: 3 - Alpha
Classifier: Environment :: Web Environment
Classifier: Intended Audience :: Developers
Classifier: License :: OSI Approved :: MIT License
Classifier: Operating System :: OS Independent
Classifier: Programming Language :: Python :: 2.7
Classifier: Programming Language :: Python :: 3.3
Classifier: Programming Language :: Python :: 3.4
Classifier: Programming Language :: Python :: 3.5
Classifier: Topic :: Internet :: WWW/HTTP :: WSGI
Requires-Dist: decorator (==4.0.9)
Requires-Dist: docutils (==0.12)
Requires-Dist: jinja2 (==2.8)
Requires-Dist: mock
Requires-Dist: six (==1.10.0)
